{
  "orders": {
    "ahmad.alweswasi@gmail.com": [
      {
        "id": "ord_1776199669779",
        "title": "Roastery Order",
        "total": "BHD 8.500",
        "status": "Completed",
        "items": [
          {
            "name": "Brazil",
            "quantity": 1
          },
          {
            "name": "Colombia",
            "quantity": 1
          }
        ],
        "createdAt": "2026-04-14T20:47:49.780Z"
      },
      {
        "id": "ord_1776160406722",
        "title": "Roastery Order",
        "total": "BHD 8.500",
        "status": "Completed",
        "createdAt": "2026-04-14T09:53:26.723Z"
      }
    ]
  }
}